dosido
